createc/Createc_global_const.yaml
createc/Createc_pyCOM.py
createc/Createc_pyFile.py
createc/__init__.py
createc/utils/DT670.py
createc/utils/__init__.py
createc/utils/data_producer.py
createc/utils/image_utils.py
createc/utils/misc.py
createc-0.0.3.dist-info/LICENSE
createc-0.0.3.dist-info/METADATA
createc-0.0.3.dist-info/WHEEL
createc-0.0.3.dist-info/top_level.txt
createc-0.0.3.dist-info/RECORD
