Metadata-Version: 2.1
Name: createc
Version: 0.0.3
Summary: A python interface with the Createc scanning probe microscope
Home-page: https://py-createc.readthedocs.io/en/latest/
Author: Chen Xu
Author-email: cxu.self@gmail.com
License: UNKNOWN
Platform: UNKNOWN
Classifier: Programming Language :: Python :: 3
Classifier: License :: OSI Approved :: MIT License
Classifier: Operating System :: Microsoft :: Windows
Classifier: Topic :: System :: Hardware :: Hardware Drivers
Classifier: Topic :: Scientific/Engineering :: Physics
Requires-Python: >=3.6
License-File: LICENSE
